Metadata-Version: 2.1
Name: teamwork
Version: 0.1.5
Summary: A Python library for building a network graph of providers in care teams from EHR data
Home-page: https://github.com/gtdelong/teamwork
Author: Grant DeLong
Author-email: ggoulae@gmail.com
License: MIT
Project-URL: Source, https://github.com/gtdelong/teamwork/
Keywords: team,collaboration,EHR
Platform: UNKNOWN
Classifier: Development Status :: 3 - Alpha
Classifier: Intended Audience :: Developers
Classifier: License :: OSI Approved :: MIT License
Classifier: Programming Language :: Python :: 3
Classifier: Programming Language :: Python :: 3.6
Classifier: Programming Language :: Python :: 3.7
Classifier: Programming Language :: Python :: 3.8
Classifier: Programming Language :: Python :: 3.9
Classifier: Programming Language :: Python :: 3 :: Only
Requires-Python: >=3.6, <4
